pyboto/Boto.py
pyboto/Exceptions.py
pyboto/__init__.py
pyboto-0.1.4.dist-info/LICENSE
pyboto-0.1.4.dist-info/METADATA
pyboto-0.1.4.dist-info/WHEEL
pyboto-0.1.4.dist-info/top_level.txt
pyboto-0.1.4.dist-info/RECORD
