Metadata-Version: 2.1
Name: pyboto
Version: 0.1.4
Summary: A simple boto3 wrapper to complete common operations in S3 such as get or put csv files, list objects and keys, etc.
Home-page: https://github.com/steven-purcell/pyboto
Author: steven-purcell
Author-email: steven.ray.purcell@gmail.com
License: Mozilla Public License Version 2.0
Platform: UNKNOWN
License-File: LICENSE
Requires-Dist: boto3
Requires-Dist: botocore
Requires-Dist: pandas
